LICENSE
README.md
setup.py
ExtendClass/Extension.py
ExtendClass/__init__.py
ExtendClass.egg-info/PKG-INFO
ExtendClass.egg-info/SOURCES.txt
ExtendClass.egg-info/dependency_links.txt
ExtendClass.egg-info/top_level.txt